technocore/__init__.py
technocore/app.py
technocore/applicationdatabase.py
technocore/contact.py
technocore/database.py
technocore/email.py
technocore/formater.py
technocore/home.py
technocore/location.py
technocore/phone.py
technocore/resources.py
technocore/themes.py
technocore/resources/licenses/technocore_license.md
technocore-0.1.12.data/data/technocore/resources/licenses/technocore_license.md
technocore-0.1.12.dist-info/DESCRIPTION.rst
technocore-0.1.12.dist-info/METADATA
technocore-0.1.12.dist-info/RECORD
technocore-0.1.12.dist-info/WHEEL
technocore-0.1.12.dist-info/entry_points.txt
technocore-0.1.12.dist-info/metadata.json
technocore-0.1.12.dist-info/top_level.txt
