Metadata-Version: 2.0
Name: technocore
Version: 0.1.12
Summary: technocore application. A command line contact book.
Home-page: UNKNOWN
Author: Thomas Rostrup Andersen
Author-email: andersen1814@gmail.com
License: BSD 2-clause
Keywords: contact book manager technocore cli tui
Platform: UNKNOWN
Requires-Dist: npyscreen
Requires-Dist: vobject
